cloudpathlib/__init__.py
cloudpathlib/anypath.py
cloudpathlib/client.py
cloudpathlib/cloudpath.py
cloudpathlib/enums.py
cloudpathlib/exceptions.py
cloudpathlib/py.typed
cloudpathlib/url_utils.py
cloudpathlib/azure/__init__.py
cloudpathlib/azure/azblobclient.py
cloudpathlib/azure/azblobpath.py
cloudpathlib/gs/__init__.py
cloudpathlib/gs/gsclient.py
cloudpathlib/gs/gspath.py
cloudpathlib/local/__init__.py
cloudpathlib/local/localclient.py
cloudpathlib/local/localpath.py
cloudpathlib/local/implementations/__init__.py
cloudpathlib/local/implementations/azure.py
cloudpathlib/local/implementations/gs.py
cloudpathlib/local/implementations/s3.py
cloudpathlib/s3/__init__.py
cloudpathlib/s3/s3client.py
cloudpathlib/s3/s3path.py
cloudpathlib-0.18.0.dist-info/LICENSE
cloudpathlib-0.18.0.dist-info/WHEEL
cloudpathlib-0.18.0.dist-info/METADATA
cloudpathlib-0.18.0.dist-info/RECORD
