Metadata-Version: 2.1
Name: cloudpathlib
Version: 0.18.0
Summary: pathlib-style classes for cloud storage services.
Keywords: pathlib,cloud storage,s3,azure blob storage,google cloud storage
Author-email: DrivenData <info@drivendata.org>
Requires-Python: >=3.7
Classifier: Intended Audience :: Developers
Classifier: License :: OSI Approved :: MIT License
Classifier: Operating System :: OS Independent
Classifier: Programming Language :: Python :: 3
Classifier: Programming Language :: Python :: 3.7
Classifier: Programming Language :: Python :: 3.8
Classifier: Programming Language :: Python :: 3.9
Classifier: Programming Language :: Python :: 3.10
Classifier: Programming Language :: Python :: 3.11
Classifier: Programming Language :: Python :: 3.12
Requires-Dist: importlib_metadata ; python_version < '3.8'
Requires-Dist: typing_extensions>4 ; python_version < '3.11'
Requires-Dist: cloudpathlib[azure] ; extra == "all"
Requires-Dist: cloudpathlib[gs] ; extra == "all"
Requires-Dist: cloudpathlib[s3] ; extra == "all"
Requires-Dist: azure-storage-blob>=12 ; extra == "azure"
Requires-Dist: google-cloud-storage ; extra == "gs"
Requires-Dist: boto3 ; extra == "s3"
Project-URL: Bug Tracker, https://github.com/drivendataorg/cloudpathlib/issues
Project-URL: Changelog, https://cloudpathlib.drivendata.org/stable/changelog/
Project-URL: Documentation, https://cloudpathlib.drivendata.org/
Project-URL: Repository, https://github.com/drivendataorg/cloudpathlib
Provides-Extra: all
Provides-Extra: azure
Provides-Extra: gs
Provides-Extra: s3
